pcrglobwb_utils/__init__.py
pcrglobwb_utils/ensembles.py
pcrglobwb_utils/obs_data.py
pcrglobwb_utils/plotting.py
pcrglobwb_utils/sim_data.py
pcrglobwb_utils/spatial_validation.py
pcrglobwb_utils/time_funcs.py
pcrglobwb_utils/utils.py
pcrglobwb_utils/water_balance.py
pcrglobwb_utils/scripts/__init__.py
pcrglobwb_utils/scripts/evaluate_poly.py
pcrglobwb_utils/scripts/evaluate_tims.py
pcrglobwb_utils/scripts/funcs.py
pcrglobwb_utils/scripts/preprocessing.py
pcrglobwb_utils-0.3.3.dist-info/AUTHORS.rst
pcrglobwb_utils-0.3.3.dist-info/LICENSE.rst
pcrglobwb_utils-0.3.3.dist-info/METADATA
pcrglobwb_utils-0.3.3.dist-info/WHEEL
pcrglobwb_utils-0.3.3.dist-info/entry_points.txt
pcrglobwb_utils-0.3.3.dist-info/top_level.txt
pcrglobwb_utils-0.3.3.dist-info/RECORD
