Metadata-Version: 2.1
Name: pcrglobwb-utils
Version: 0.3.3
Summary: Handy functions to work with PCR-GLOBWB input and output
Home-page: https://pcrglobwb-utils.readthedocs.io/
Author: Jannis M. Hoch
Author-email: j.m.hoch@uu.nl
License: GNU General Public License v3
Keywords: pcrglobwb_utils
Platform: UNKNOWN
Classifier: Development Status :: 4 - Beta
Classifier: Intended Audience :: Developers
Classifier: License :: OSI Approved :: GNU General Public License v3 (GPLv3)
Classifier: Natural Language :: English
Classifier: Programming Language :: Python :: 3
Classifier: Programming Language :: Python :: 3.7
Classifier: Programming Language :: Python :: 3.8
Classifier: Programming Language :: Python :: 3.9
Requires-Python: >=3.7
License-File: LICENSE.rst
License-File: AUTHORS.rst
Requires-Dist: rasterio (>=1.1)
Requires-Dist: xarray (>=0.18)
Requires-Dist: pandas (>=1.2)
Requires-Dist: numpy (>=1.20)
Requires-Dist: matplotlib (>=3.2.0)
Requires-Dist: geopandas (>=0.9)
Requires-Dist: rioxarray (>=0.4)
Requires-Dist: click (>=7.1.1)
Requires-Dist: scipy
Requires-Dist: xlrd (>=2.0)
Requires-Dist: openpyxl (>=3.0.7)
Requires-Dist: descartes
Requires-Dist: spotpy (>=1.5.8)
Requires-Dist: netcdf4
Requires-Dist: setuptools (>=49.6)
Requires-Dist: jinja2 (==2.11.3)
Requires-Dist: pyyaml
Requires-Dist: dask (==2021.10.0)
